eslogging/__init__.py
eslogging/handlers.py
eslogging/serializers.py
tests/__init__.py
tests/test_cmreshandler.py
tests/test_cmresserializer.py
LoggingEsHandler-1.0.4.dist-info/LICENSE.md
LoggingEsHandler-1.0.4.dist-info/METADATA
LoggingEsHandler-1.0.4.dist-info/WHEEL
LoggingEsHandler-1.0.4.dist-info/top_level.txt
LoggingEsHandler-1.0.4.dist-info/RECORD
